vidlist.py
vidlist-0.0.4.dist-info/LICENSE.txt
vidlist-0.0.4.dist-info/METADATA
vidlist-0.0.4.dist-info/WHEEL
vidlist-0.0.4.dist-info/entry_points.txt
vidlist-0.0.4.dist-info/top_level.txt
vidlist-0.0.4.dist-info/RECORD
